<?xml version="1.0" encoding="UTF-8"?>
<objects serializationModel="Studio.02.02.00">
	<object class="AudioFile" id="{cb8d87fa-e73d-4453-a87d-3c5e89a941df}">
		<property name="assetPath">
			<value>Ambience/514865__matrixxx__elevator-ping-02.wav</value>
		</property>
		<property name="frequencyInKHz">
			<value>44.0999985</value>
		</property>
		<property name="channelCount">
			<value>2</value>
		</property>
		<property name="length">
			<value>1.5095691609977324</value>
		</property>
		<relationship name="masterAssetFolder">
			<destination>{c4d8db74-fc69-40b6-a380-5a79492a0b43}</destination>
		</relationship>
	</object>
</objects>
